function_cache/__init__.py
function_cache/backends.py
function_cache/decorators.py
function_cache/utils.py
function_cache-0.2.0.dist-info/LICENSE
function_cache-0.2.0.dist-info/METADATA
function_cache-0.2.0.dist-info/WHEEL
function_cache-0.2.0.dist-info/top_level.txt
function_cache-0.2.0.dist-info/RECORD
