Metadata-Version: 2.1
Name: function-cache
Version: 0.2.0
Summary: A Django-based convenience decorator for caching results of functions to various backends.
Home-page: https://github.com/fivehealth/function-cache
Author: 5 Health Inc
Author-email: hello@botmd.io
License: MIT License
Keywords: django cache
Platform: UNKNOWN
Classifier: Development Status :: 4 - Beta
Classifier: Programming Language :: Python :: 3
Classifier: Framework :: Django
Classifier: Framework :: Django :: 2.2
Classifier: Framework :: Django :: 3.0
Classifier: Framework :: Django :: 3.1
Classifier: License :: OSI Approved :: MIT License
Requires-Python: >=3
Requires-Dist: Django (>2.0)
